{
  "configVersion": 1,
  "timestamp": 1766689616856,
  "index": "/SaltorSystem/index.html",
  "assetGroups": [
    {
      "name": "app",
      "installMode": "prefetch",
      "updateMode": "prefetch",
      "cacheQueryOptions": {
        "ignoreVary": true
      },
      "urls": [
        "/SaltorSystem/118.dff679f248610dac.js",
        "/SaltorSystem/133.0e90bdb4420287ea.js",
        "/SaltorSystem/223.259bb3974bdb9f45.js",
        "/SaltorSystem/226.28ca0cf67e17a768.js",
        "/SaltorSystem/234.46823621869c47dd.js",
        "/SaltorSystem/289.be2d1be26e45f128.js",
        "/SaltorSystem/313.a021651850b343b7.js",
        "/SaltorSystem/328.a5aad6704045a0e4.js",
        "/SaltorSystem/353.4a4e0bc80184e1dd.js",
        "/SaltorSystem/368.764f033b209aee2a.js",
        "/SaltorSystem/377.b1a772055fe9703f.js",
        "/SaltorSystem/388.c9d888cd1c81eac6.js",
        "/SaltorSystem/389.060b32bc2226c918.js",
        "/SaltorSystem/403.86aeaa132e7c2b89.js",
        "/SaltorSystem/456.4e539d411512e310.js",
        "/SaltorSystem/47.1d5a415ac4adc455.js",
        "/SaltorSystem/483.0df223589281b2ec.js",
        "/SaltorSystem/486.c5a8d103bd2decbb.js",
        "/SaltorSystem/503.dd7212c01e95e843.js",
        "/SaltorSystem/543.fa9e138275a0baa1.js",
        "/SaltorSystem/556.d3fed48a45f8634e.js",
        "/SaltorSystem/654.0b3ca15ea8aad5a1.js",
        "/SaltorSystem/655.f5ceb6b916ad8460.js",
        "/SaltorSystem/665.eb2370071b5e3e96.js",
        "/SaltorSystem/695.fc45e9e50f66c25c.js",
        "/SaltorSystem/730.522eef17def8bcf3.js",
        "/SaltorSystem/746.3a2c2931ae087a7c.js",
        "/SaltorSystem/749.d060000b1bb43e85.js",
        "/SaltorSystem/797.baa1130b9a89d237.js",
        "/SaltorSystem/798.631d9dce225cdade.js",
        "/SaltorSystem/827.03c491fa5b963935.js",
        "/SaltorSystem/885.c49803e7e6b1c77a.js",
        "/SaltorSystem/896.a7fbfba46ae4a4e4.js",
        "/SaltorSystem/898.41899a064e904f2c.js",
        "/SaltorSystem/common.109a407e373f54bf.js",
        "/SaltorSystem/favicon.ico",
        "/SaltorSystem/index.html",
        "/SaltorSystem/main.f0f02b4e7843bef2.js",
        "/SaltorSystem/manifest.webmanifest",
        "/SaltorSystem/polyfills.4240d9f215fcc783.js",
        "/SaltorSystem/runtime.c31f8e9bc711eac9.js",
        "/SaltorSystem/scripts.57bd936209690c16.js",
        "/SaltorSystem/styles.19360a9aba887258.css"
      ],
      "patterns": []
    },
    {
      "name": "assets",
      "installMode": "lazy",
      "updateMode": "prefetch",
      "cacheQueryOptions": {
        "ignoreVary": true
      },
      "urls": [
        "/SaltorSystem/assets/logo.jpg",
        "/SaltorSystem/assets/logo2.png"
      ],
      "patterns": []
    }
  ],
  "dataGroups": [],
  "hashTable": {
    "/SaltorSystem/118.dff679f248610dac.js": "cd4057946dbeeba2ecf29a940b03141025b7b6e3",
    "/SaltorSystem/133.0e90bdb4420287ea.js": "b5cf3b959c93b9572811e08328e0b024baa70261",
    "/SaltorSystem/223.259bb3974bdb9f45.js": "8636d1f63bc6bcbcdbef898af99b4440d44b3313",
    "/SaltorSystem/226.28ca0cf67e17a768.js": "007af812166de27b2c35f237e281e0cd7cd5f33f",
    "/SaltorSystem/234.46823621869c47dd.js": "238e304cee07fa7a87dcf599e1ad308bf181bf2f",
    "/SaltorSystem/289.be2d1be26e45f128.js": "ada375557174c59d274b3e1db09a82c7ec0e7898",
    "/SaltorSystem/313.a021651850b343b7.js": "7a6917c4b5ffc63f4d3c1d63d4165dcd4ad588d0",
    "/SaltorSystem/328.a5aad6704045a0e4.js": "f3c1709fdce82dadba60bad8ea4825aa39af02b3",
    "/SaltorSystem/353.4a4e0bc80184e1dd.js": "0f8a263a89ef9de45ef77128e7109c82d0d12da4",
    "/SaltorSystem/368.764f033b209aee2a.js": "8ae562dc95e6561441c297dd2087370ff9e6a39e",
    "/SaltorSystem/377.b1a772055fe9703f.js": "8a0c694e06c0745ec800a556e4b64d3b4ddbdf40",
    "/SaltorSystem/388.c9d888cd1c81eac6.js": "08904e3e63a66b04e4a5e859619e8183448b2839",
    "/SaltorSystem/389.060b32bc2226c918.js": "cc6396a3b2d6c13d70281692db63879770a4138e",
    "/SaltorSystem/403.86aeaa132e7c2b89.js": "f32a672f6392ba280aa3c4147ab658db6ad6de23",
    "/SaltorSystem/456.4e539d411512e310.js": "155a967c56fd52cd7e8b79b059419c52d9d2c242",
    "/SaltorSystem/47.1d5a415ac4adc455.js": "62fcf72e76c6080e9fd7eefe40ae970e296836f1",
    "/SaltorSystem/483.0df223589281b2ec.js": "d097c1093af2fab7db5d4ab45bbd5cd4a35233c3",
    "/SaltorSystem/486.c5a8d103bd2decbb.js": "7323cc71f00ccbe11a8da650ba7e6a88f7359380",
    "/SaltorSystem/503.dd7212c01e95e843.js": "88e31de5ba35c4e41a6476e5f3e045cc62530581",
    "/SaltorSystem/543.fa9e138275a0baa1.js": "37f71f35c938748353cf26d16c253b73c949fbde",
    "/SaltorSystem/556.d3fed48a45f8634e.js": "5fda90ef2d0a4c796a622e01059147dcd7dc5218",
    "/SaltorSystem/654.0b3ca15ea8aad5a1.js": "80a6b1bb887a7fd597d7785a9773d58daae23555",
    "/SaltorSystem/655.f5ceb6b916ad8460.js": "a589681ab5c30238370c14efecd83b255e688983",
    "/SaltorSystem/665.eb2370071b5e3e96.js": "337f801ad2c652c8f7a1c0bd055587023507f59f",
    "/SaltorSystem/695.fc45e9e50f66c25c.js": "9d373ae146aaaf106202196b6130b1d0f30ce278",
    "/SaltorSystem/730.522eef17def8bcf3.js": "a9c271e23952d1f9f0f38939b0724052e63d090b",
    "/SaltorSystem/746.3a2c2931ae087a7c.js": "3b46053c59786145e6064198d086618d6e9d929b",
    "/SaltorSystem/749.d060000b1bb43e85.js": "ebc2cc551cec2a929e3080223cdb2368a4eed33c",
    "/SaltorSystem/797.baa1130b9a89d237.js": "b94a63b54509fe539a697731fbf73d589cc2be07",
    "/SaltorSystem/798.631d9dce225cdade.js": "d2c356e5fcef74a29ad2a56564eb6b14c12a6a43",
    "/SaltorSystem/827.03c491fa5b963935.js": "e6ef90e54ae0724040f14bdea6632a751129fb6a",
    "/SaltorSystem/885.c49803e7e6b1c77a.js": "e92e3c9f32a513ddab6c3a636c94f9c032e1e445",
    "/SaltorSystem/896.a7fbfba46ae4a4e4.js": "ee7ea14ac161a57bcb9091fe4d8983a00da812e7",
    "/SaltorSystem/898.41899a064e904f2c.js": "33c139c267587bf06a042bdf215c72467901d5ed",
    "/SaltorSystem/assets/logo.jpg": "d4912bcb011b306949f96a2545bfbc81cc3362ec",
    "/SaltorSystem/assets/logo2.png": "cfd8b0ca5c5d402637087bf6eb4012fe4ad78e37",
    "/SaltorSystem/common.109a407e373f54bf.js": "ceb6ec87511d88b85d8d02d39e28edb20c651dc7",
    "/SaltorSystem/favicon.ico": "22f6a4a3bcaafafb0254e0f2fa4ceb89e505e8b2",
    "/SaltorSystem/index.html": "144ba17858c161d1851f5c5656a2c0ebee2a7762",
    "/SaltorSystem/main.f0f02b4e7843bef2.js": "3a95fd2f996cc1fc7dd4065262920d5c05596932",
    "/SaltorSystem/manifest.webmanifest": "7821b675ca322281ff85d4b0365c60031f710b79",
    "/SaltorSystem/polyfills.4240d9f215fcc783.js": "8d77d2feda492ea9f6c4898d76b4b8ee0c030147",
    "/SaltorSystem/runtime.c31f8e9bc711eac9.js": "49d481419c49cb613988ffd394a17216caea35c3",
    "/SaltorSystem/scripts.57bd936209690c16.js": "a3aa3506362e7db8195778428b68e0c4352310bb",
    "/SaltorSystem/styles.19360a9aba887258.css": "377d96104ef6b554a7a54ffdd151a4afc8d7aed8"
  },
  "navigationUrls": [
    {
      "positive": true,
      "regex": "^\\/.*$"
    },
    {
      "positive": false,
      "regex": "^\\/(?:.+\\/)?[^/]*\\.[^/]*$"
    },
    {
      "positive": false,
      "regex": "^\\/(?:.+\\/)?[^/]*__[^/]*$"
    },
    {
      "positive": false,
      "regex": "^\\/(?:.+\\/)?[^/]*__[^/]*\\/.*$"
    }
  ],
  "navigationRequestStrategy": "performance"
}